{
  "name": "hdfs3-sync",
  "config": {
    "connector.class": "io.confluent.connect.hdfs3.Hdfs3SinkConnector",
    "tasks.max": "1",
    "topics": "source.mirroring",

    "hdfs.url": "hdfs://hadoop-namenode:9000",
    "flush.size": "3",
    "format.class": "io.confluent.connect.hdfs3.avro.AvroFormat",

    "confluent.topic.bootstrap.servers": "kafka-replica-1:9093,kafka-replica-2:9093,kafka-replica-3:9093",
    "confluent.topic.security.protocol": "SSL",
    "confluent.topic.ssl.truststore.location": "/etc/kafka/certs/truststore.jks",
    "confluent.topic.ssl.truststore.password": "changeit",
    "confluent.topic.ssl.keystore.location": "/etc/kafka/certs/client.p12",
    "confluent.topic.ssl.keystore.password": "changeit",
    "confluent.topic.ssl.key.password": "changeit",
    "confluent.topic.ssl.keystore.type": "PKCS12",

    "consumer.override.bootstrap.servers": "kafka-replica-1:9093,kafka-replica-2:9093,kafka-replica-3:9093",
    "consumer.override.security.protocol": "SASL_SSL",
    "consumer.override.sasl.mechanism": "PLAIN",
    "consumer.override.sasl.jaas.config": "org.apache.kafka.common.security.plain.PlainLoginModule required username=\"hdfs\" password=\"hdfs_pass\";",
    "consumer.override.ssl.truststore.location": "/etc/kafka/certs/truststore.jks",
    "consumer.override.ssl.truststore.password": "changeit",
    "consumer.override.ssl.keystore.location": "/etc/kafka/certs/client.p12",
    "consumer.override.ssl.keystore.password": "changeit",
    "consumer.override.ssl.key.password": "changeit",
    "consumer.override.ssl.keystore.type": "PKCS12",

    "admin.override.security.protocol": "SASL_SSL",
    "admin.override.sasl.mechanism": "PLAIN",
    "admin.override.sasl.jaas.config": "org.apache.kafka.common.security.plain.PlainLoginModule required username=\"hdfs\" password=\"hdfs_pass\";",
    "admin.override.ssl.truststore.location": "/etc/kafka/certs/truststore.jks",
    "admin.override.ssl.truststore.password": "changeit",
    "admin.override.ssl.keystore.location": "/etc/kafka/certs/client.p12",
    "admin.override.ssl.keystore.password": "changeit",
    "admin.override.ssl.key.password": "changeit",
    "admin.override.ssl.keystore.type": "PKCS12"
  }
}